{
  "raw_response": "{\n  \"candidates\": [\n    {\n      \"entity\": \"interactive computer service\",\n      \"type\": \"technology\",\n      \"attribute\": \"exemption\",\n      \"value\": \"liability\",\n      \"entity_evidence\": [\n        {\"start\": 0, \"end\": 24, \"text\": \"An interactive computer service\"}\n      ]\n    ,\n    \"type_evidence\": [\n        {\"start\": 0, \"end\": 24, \"text\": \"An interactive computer service\"}\n      ]\n    ,\n    \"attribute_evidence\": [\n        {\"start\": 0, \"end\": 24, \"text\": \"An interactive computer service\"}\n      ]\n    ,\n    \"value_evidence\": [\n        {\"start\": 0, \"end\": 24, \"text\": \"An interactive computer service\"}\n      ]\n    },\n    {\n      \"entity\": \"artificial intelligence\",\n      \"type\": \"technology\",\n      \"attribute\": \"definition\",\n      \"value\": \"machine-based system\",\n      \"entity_evidence\": [\n        {\"start\": 0, \"end\": 18, \"text\": \"artificial intelligence\"}\n      ]\n    ,\n    \"type_evidence\": [\n        {\"start\": 0, \"end\": 18, \"text\": \"artificial intelligence\"}\n      ]\n    ,\n    \"attribute_evidence\": [\n        {\"start\": 0, \"end\": 18, \"text\": \"artificial intelligence\"}\n      ]\n    ,\n    \"value_evidence\": [\n        {\"start\": 0, \"end\": 18, \"text\": \"artificial intelligence\"}\n      ]\n    }\n  ]\n}"
}