{
  "raw_response": "{\n  \"candidates\": [\n    {\n      \"entity\": \"GARVEE bonds\",\n      \"type\": \"technology\",\n      \"attribute\": \"restriction\",\n      \"value\": \"extremely restrictive\",\n      \"entity_evidence\": [\n        {\"start\": 0, \"end\": 7, \"text\": \"GARVEE\"}\n      ]\n    ,\n    \"type_evidence\": [\n      {\"start\": 0, \"end\": 7, \"text\": \"GARVEE\"}\n    ]\n    ,\n    \"attribute_evidence\": [\n      {\"start\": 0, \"end\": 7, \"text\": \"GARVEE\"}\n    ]\n    ,\n    \"value_evidence\": [\n      {\"start\": 0, \"end\": 7, \"text\": \"GARVEE\"}\n    ]\n  },\n  {\n    \"entity\": \"California Transportation Commission\",\n    \"type\": \"government agency\",\n    \"attribute\": \"restriction\",\n    \"value\": \"extremely restrictive\",\n    \"entity_evidence\": [\n      {\"start\": 0, \"end\": 24, \"text\": \"California Transportation Commission\"}\n    ]\n  ,\n  \"type_evidence\": [\n    {\"start\": 0, \"end\": 24, \"text\": \"California Transportation Commission\"}\n  ]\n  ,\n  \"attribute_evidence\": [\n    {\"start\": 0, \"end\": 24, \"text\": \"California Transportation Commission\"}\n  ]\n  ,\n  \"value_evidence\": [\n    {\"start\": 0, \"end\": 24, \"text\": \"California Transportation Commission\"}\n  ]\n  }\n  ]}"
}