{
  "raw_response": "{\n  \"candidates\": [\n    {\n      \"entity\": \"Department of Finance\",\n      \"type\": \"government agency\",\n      \"attribute\": \"restriction\",\n      \"value\": \"conditional\",\n      \"entity_evidence\": [\n        {\"start\": 698, \"end\": 714, \"text\": \"the Department of Finance may transfer up to $698,000 as a loan\"}\n      ],\n      \"type_evidence\": [\n        {\"start\": 698, \"end\": 714, \"text\": \"the Department of Finance may transfer up to $698,000 as a loan\"}\n      ],\n      \"attribute_evidence\": [\n        {\"start\": 698, \"end\": 714, \"text\": \"the Department of Finance may transfer up to $698,000 as a loan\"}\n      ],\n      \"value_evidence\": [\n        {\"start\": 698, \"end\": 714, \"text\": \"the Department of Finance may transfer up to $698,000 as a loan\"}\n      ]\n    },\n    {\n      \"entity\": \"Textile Stewardship Recovery Fund\",\n      \"type\": \"infrastructure\",\n      \"attribute\": \"restriction\",\n      \"value\": \"conditional\",\n      \"entity_evidence\": [\n        {\"start\": 1348, \"end\": 1365, \"text\": \"the Textile Stewardship Recovery Fund\"}\n      ],\n      \"type_evidence\": [\n        {\"start\": 1348, \"end\": 1365, \"text\": \"the Textile Stewardship Recovery Fund\"}\n      ],\n      \"attribute_evidence\": [\n        {\"start\": 1348, \"end\": 1365, \"text\": \"the Textile Stewardship Recovery Fund\"}\n      ],\n      \"value_evidence\": [\n        {\"start\": 1348, \"end\": 1365, \"text\": \"the Textile Stewardship Recovery Fund\"}\n      ]\n    }\n  ]\n}"
}