[
  {
    "candidate_id": 8164589001617068634,
    "entity": "Internal borrowing",
    "type": "technology",
    "attribute": "restriction",
    "value": "most economical manner",
    "entity_evidence": [
      {
        "span_id": 7519414072451399094,
        "start": 1710385,
        "end": 1710398,
        "text": "rrowing. In conducting internal borrowing",
        "chunk_id": 13968508032208768831
      }
    ],
    "type_evidence": [
      {
        "span_id": 415228429998444110,
        "start": 1710385,
        "end": 1710398,
        "text": "rrowing. In conducting internal borrowing",
        "chunk_id": 13968508032208768831
      }
    ],
    "attribute_evidence": [
      {
        "span_id": 13775733747429339750,
        "start": 1710385,
        "end": 1710398,
        "text": "rrowing. In conducting internal borrowing",
        "chunk_id": 13968508032208768831
      }
    ],
    "value_evidence": [
      {
        "span_id": 6979183870101558580,
        "start": 1710385,
        "end": 1710398,
        "text": "rrowing. In conducting internal borrowing",
        "chunk_id": 13968508032208768831
      }
    ]
  },
  {
    "candidate_id": 88816045681152808,
    "entity": "Internal borrowable funds",
    "type": "technology",
    "attribute": "restriction",
    "value": "higher rate of interest payments",
    "entity_evidence": [
      {
        "span_id": 3509426526714618069,
        "start": 1710399,
        "end": 1710416,
        "text": "Internal borrowable funds that require a higher rate of interest payments",
        "chunk_id": 13968508032208768831
      }
    ],
    "type_evidence": [
      {
        "span_id": 936613909180702988,
        "start": 1710399,
        "end": 1710416,
        "text": "Internal borrowable funds that require a higher rate of interest payments",
        "chunk_id": 13968508032208768831
      }
    ],
    "attribute_evidence": [
      {
        "span_id": 2734957758441976163,
        "start": 1710399,
        "end": 1710416,
        "text": "Internal borrowable funds that require a higher rate of interest payments",
        "chunk_id": 13968508032208768831
      }
    ],
    "value_evidence": [
      {
        "span_id": 1245549797597575085,
        "start": 1710399,
        "end": 1710416,
        "text": "Internal borrowable funds that require a higher rate of interest payments",
        "chunk_id": 13968508032208768831
      }
    ]
  }
]