{
  "raw_response": "{\n  \"candidates\": [\n    {\n      \"entity\": \"Secretary for Environmental Protection\",\n      \"type\": \"government agency\",\n      \"attribute\": \"support\",\n      \"value\": \"payable from the State Water Quality Control Fund\",\n      \"entity_evidence\": [\n        {\"start\": 0, \"end\": 23, \"text\": \"For support of Secretary for Environmental Protection, payable from the State Water Quality Control Fund\"}\n      ],\n      \"type_evidence\": [\n        {\"start\": 0, \"end\": 23, \"text\": \"For support of Secretary for Environmental Protection, payable from the State Water Quality Control Fund\"}\n      ],\n      \"attribute_evidence\": [\n        {\"start\": 0, \"end\": 23, \"text\": \"For support of Secretary for Environmental Protection, payable from the State Water Quality Control Fund\"}\n      ],\n      \"value_evidence\": [\n        {\"start\": 0, \"end\": 23, \"text\": \"For support of Secretary for Environmental Protection, payable from the State Water Quality Control Fund\"}\n      ]\n    },\n    {\n      \"entity\": \"Secretary of Labor and Workforce Development\",\n      \"type\": \"government agency\",\n      \"attribute\": \"support\",\n      \"value\": \"payable from the Labor and Workforce Development Fund\",\n      \"entity_evidence\": [\n        {\"start\": 0, \"end\": 34, \"text\": \"For support of Secretary of Labor and Workforce Development, payable from the Labor and Workforce Development Fund\"}\n      ],\n      \"type_evidence\": [\n        {\"start\": 0, \"end\": 34, \"text\": \"For support of Secretary of Labor and Workforce Development, payable from the Labor and Workforce Development Fund\"}\n      ],\n      \"attribute_evidence\": [\n        {\"start\": 0, \"end\": 34, \"text\": \"For support of Secretary of Labor and Workforce Development, payable from the Labor and Workforce Development Fund\"}\n      ],\n      \"value_evidence\": [\n        {\"start\": 0, \"end\": 34, \"text\": \"For support of Secretary of Labor and Workforce Development, payable from the Labor and Workforce Development Fund\"}\n      ]\n    }\n  ]\n}"
}