[
  {
    "candidate_id": 16300491591475070606,
    "entity": "Department of Fish and Wildlife",
    "type": "government agency",
    "attribute": "support",
    "value": "payable from the Fish and Game Preservation Fund",
    "entity_evidence": [
      {
        "span_id": 17891932413161545271,
        "start": 552043,
        "end": 552067,
        "text": "Department of Fish and Wildlife",
        "chunk_id": 18203587796331557670
      }
    ],
    "type_evidence": [
      {
        "span_id": 2327468240560070518,
        "start": 552068,
        "end": 552086,
        "text": "government agency",
        "chunk_id": 18203587796331557670
      }
    ],
    "attribute_evidence": [
      {
        "span_id": 6627212321544546430,
        "start": 552087,
        "end": 552107,
        "text": "support",
        "chunk_id": 18203587796331557670
      }
    ],
    "value_evidence": [
      {
        "span_id": 6544054055580586221,
        "start": 552108,
        "end": 552166,
        "text": "payable from the Fish and Game Preservation Fund",
        "chunk_id": 18203587796331557670
      }
    ]
  },
  {
    "candidate_id": 14311353485672444482,
    "entity": "Department of Fish and Wildlife",
    "type": "government agency",
    "attribute": "support",
    "value": "payable from the Marine Invasive Species Control Fund",
    "entity_evidence": [
      {
        "span_id": 15101403864064703266,
        "start": 552043,
        "end": 552067,
        "text": "Department of Fish and Wildlife",
        "chunk_id": 18203587796331557670
      }
    ],
    "type_evidence": [
      {
        "span_id": 150765119217715103,
        "start": 552068,
        "end": 552086,
        "text": "government agency",
        "chunk_id": 18203587796331557670
      }
    ],
    "attribute_evidence": [
      {
        "span_id": 3771744056725359281,
        "start": 552087,
        "end": 552107,
        "text": "support",
        "chunk_id": 18203587796331557670
      }
    ],
    "value_evidence": [
      {
        "span_id": 5407300863907408505,
        "start": 552108,
        "end": 552136,
        "text": "payable from the Marine Invasive Species Control Fund",
        "chunk_id": 18203587796331557670
      }
    ]
  }
]