[
  {
    "candidate_id": 14595397065923118749,
    "entity": "State Energy Resources Conservation and Development Commission",
    "type": "government agency",
    "attribute": "restriction",
    "value": "until June 30, 2029",
    "entity_evidence": [
      {
        "span_id": 2851080225495363941,
        "start": 473758,
        "end": 473778,
        "text": "State Energy Resources Conservation and Development Commission",
        "chunk_id": 5025315919950534665
      }
    ],
    "type_evidence": [
      {
        "span_id": 13017446298837205934,
        "start": 473758,
        "end": 473778,
        "text": "government agency",
        "chunk_id": 5025315919950534665
      }
    ],
    "attribute_evidence": [
      {
        "span_id": 2978326386820254155,
        "start": 473758,
        "end": 473778,
        "text": "restriction",
        "chunk_id": 5025315919950534665
      }
    ],
    "value_evidence": [
      {
        "span_id": 5260175543631437111,
        "start": 473758,
        "end": 473778,
        "text": "until June 30, 2029",
        "chunk_id": 5025315919950534665
      }
    ]
  },
  {
    "candidate_id": 6230988584545718852,
    "entity": "Public Utilities Commission",
    "type": "government agency",
    "attribute": "promotion",
    "value": "approved by the Public Utilities Commission",
    "entity_evidence": [
      {
        "span_id": 9345831702374747780,
        "start": 473758,
        "end": 473778,
        "text": "Public Utilities Commission",
        "chunk_id": 5025315919950534665
      }
    ],
    "type_evidence": [
      {
        "span_id": 13516801662073542794,
        "start": 473758,
        "end": 473778,
        "text": "government agency",
        "chunk_id": 5025315919950534665
      }
    ],
    "attribute_evidence": [
      {
        "span_id": 5331877583637663064,
        "start": 473758,
        "end": 473778,
        "text": "promotion",
        "chunk_id": 5025315919950534665
      }
    ],
    "value_evidence": [
      {
        "span_id": 12834408786506666300,
        "start": 473758,
        "end": 473778,
        "text": "approved by the Public Utilities Commission",
        "chunk_id": 5025315919950534665
      }
    ]
  }
]