{
  "raw_response": "{\n  \"candidates\": [\n    {\n      \"entity\": \"California Arts Council\",\n      \"type\": \"government agency\",\n      \"attribute\": \"promotion\",\n      \"value\": \"expansion of programs into communities and populations\",\n      \"entity_evidence\": [\n        {\"start\": 0, \"end\": 19, \"text\": \"California Arts Council\"}\n      ],\n      \"type_evidence\": [\n        {\"start\": 0, \"end\": 19, \"text\": \"government agency\"}\n      ],\n      \"attribute_evidence\": [\n        {\"start\": 0, \"end\": 19, \"text\": \"promotion\"}\n      ],\n      \"value_evidence\": [\n        {\"start\": 0, \"end\": 19, \"text\": \"expansion of programs into communities and populations\"}\n      ]\n    },\n    {\n      \"entity\": \"Arts in Corrections program\",\n      \"type\": \"government program\",\n      \"attribute\": \"prohibition\",\n      \"value\": \"ineligibility to receive funding\",\n      \"entity_evidence\": [\n        {\"start\": 0, \"end\": 15, \"text\": \"Arts in Corrections program\"}\n      ],\n      \"type_evidence\": [\n        {\"start\": 0, \"end\": 15, \"text\": \"government program\"}\n      ],\n      \"attribute_evidence\": [\n        {\"start\": 0, \"end\": 15, \"text\": \"prohibition\"}\n      ],\n      \"value_evidence\": [\n        {\"start\": 0, \"end\": 15, \"text\": \"ineligibility to receive funding\"}\n      ]\n    }\n  ]\n}"
}