[
  {
    "group_id": 17719561599241376076,
    "candidate_ids": [
      11688629757594388143,
      2673019035618444687
    ],
    "field_score_matrix": [
      [
        1.0,
        1.0,
        1.0,
        1.0
      ],
      [
        1.0,
        1.0,
        1.0,
        1.0
      ]
    ],
    "field_order": [
      "entity",
      "type",
      "attribute",
      "value"
    ]
  },
  {
    "group_id": 11900256345383233425,
    "candidate_ids": [
      7630036418510712561,
      6136053273197912052
    ],
    "field_score_matrix": [
      [
        1.0,
        1.0,
        1.0,
        1.0
      ],
      [
        1.0,
        1.0,
        1.0,
        1.0
      ]
    ],
    "field_order": [
      "entity",
      "type",
      "attribute",
      "value"
    ]
  },
  {
    "group_id": 7948355391355650293,
    "candidate_ids": [
      9412577804415490358,
      14441377392394045052
    ],
    "field_score_matrix": [
      [
        1.0,
        1.0,
        1.0,
        1.0
      ],
      [
        1.0,
        1.0,
        1.0,
        1.0
      ]
    ],
    "field_order": [
      "entity",
      "type",
      "attribute",
      "value"
    ]
  },
  {
    "group_id": 10759065743291944045,
    "candidate_ids": [
      7887057927734284200,
      4983557891837323477
    ],
    "field_score_matrix": [
      [
        0.0,
        0.0,
        0.0,
        0.0
      ],
      [
        0.0,
        0.0,
        0.0,
        0.0
      ]
    ],
    "field_order": [
      "entity",
      "type",
      "attribute",
      "value"
    ]
  }
]