[
  {
    "group_id": 12439197435538009136,
    "candidate_ids": [
      17267394162468360929,
      1438818723000840798
    ],
    "field_score_matrix": [
      [
        0.9,
        0.8,
        0.0,
        0.0
      ],
      [
        0.0,
        0.0,
        0.9,
        0.8
      ]
    ],
    "field_order": [
      "entity",
      "type",
      "attribute",
      "value"
    ]
  },
  {
    "group_id": 17381841480119323407,
    "candidate_ids": [
      6055596107320144086,
      11274469127504530341
    ],
    "field_score_matrix": [
      [
        0.8,
        0.9,
        0.9,
        0.9
      ],
      [
        0.9,
        0.9,
        0.9,
        0.9
      ]
    ],
    "field_order": [
      "entity",
      "type",
      "attribute",
      "value"
    ]
  },
  {
    "group_id": 2575711539171783149,
    "candidate_ids": [
      6403811352940076846,
      5487323100657235103
    ],
    "field_score_matrix": [
      [
        0.8,
        0.9,
        0.0,
        0.0
      ],
      [
        0.0,
        0.0,
        0.9,
        0.9
      ]
    ],
    "field_order": [
      "entity",
      "type",
      "attribute",
      "value"
    ]
  },
  {
    "group_id": 932977832132097009,
    "candidate_ids": [
      9532699742771596726,
      5953327223089452889
    ],
    "field_score_matrix": [
      [
        0.0,
        0.0,
        0.8,
        0.0
      ],
      [
        0.0,
        0.0,
        0.9,
        0.9
      ]
    ],
    "field_order": [
      "entity",
      "type",
      "attribute",
      "value"
    ]
  },
  {
    "group_id": 3209416854368542274,
    "candidate_ids": [
      5244246867925000721,
      11013115425202771589
    ],
    "field_score_matrix": [
      [
        0.0,
        0.0,
        0.8,
        0.0
      ],
      [
        0.0,
        0.0,
        0.9,
        0.9
      ]
    ],
    "field_order": [
      "entity",
      "type",
      "attribute",
      "value"
    ]
  },
  {
    "group_id": 5466043363827716415,
    "candidate_ids": [
      11239866989987228560,
      11130077197885213017
    ],
    "field_score_matrix": [
      [
        0.0,
        0.0,
        0.8,
        0.0
      ],
      [
        0.0,
        0.0,
        0.9,
        0.9
      ]
    ],
    "field_order": [
      "entity",
      "type",
      "attribute",
      "value"
    ]
  },
  {
    "group_id": 8926821898007226778,
    "candidate_ids": [
      5620792656918152428,
      10046085245756867548
    ],
    "field_score_matrix": [
      [
        0.8,
        0.9,
        0.9,
        0.9
      ],
      [
        0.9,
        0.9,
        0.9,
        0.9
      ]
    ],
    "field_order": [
      "entity",
      "type",
      "attribute",
      "value"
    ]
  },
  {
    "group_id": 10656573653044526820,
    "candidate_ids": [
      13255074676089053416,
      2530000753157692345
    ],
    "field_score_matrix": [
      [
        0.8,
        0.9,
        0.9,
        0.9
      ],
      [
        0.9,
        0.9,
        0.9,
        0.9
      ]
    ],
    "field_order": [
      "entity",
      "type",
      "attribute",
      "value"
    ]
  },
  {
    "group_id": 12408438803337778863,
    "candidate_ids": [
      13505867551489991708,
      14788225350551356536
    ],
    "field_score_matrix": [
      [
        0.8,
        0.9,
        0.9,
        0.9
      ],
      [
        0.9,
        0.9,
        0.9,
        0.9
      ]
    ],
    "field_order": [
      "entity",
      "type",
      "attribute",
      "value"
    ]
  },
  {
    "group_id": 11088555660750706052,
    "candidate_ids": [
      10882626230223141843,
      9168887424680534936
    ],
    "field_score_matrix": [
      [
        0.8,
        0.9,
        0.9,
        0.9
      ],
      [
        0.9,
        0.9,
        0.9,
        0.9
      ]
    ],
    "field_order": [
      "entity",
      "type",
      "attribute",
      "value"
    ]
  },
  {
    "group_id": 5957853625852208036,
    "candidate_ids": [
      15454759224257646449,
      5374525546249545475
    ],
    "field_score_matrix": [
      [
        0.8,
        0.9,
        0.9,
        0.9
      ],
      [
        0.9,
        0.9,
        0.9,
        0.9
      ]
    ],
    "field_order": [
      "entity",
      "type",
      "attribute",
      "value"
    ]
  },
  {
    "group_id": 15530833336346327403,
    "candidate_ids": [
      4546376228459824126,
      649119607855682811
    ],
    "field_score_matrix": [
      [
        0.8,
        0.9,
        0.9,
        0.9
      ],
      [
        0.9,
        0.9,
        0.9,
        0.9
      ]
    ],
    "field_order": [
      "entity",
      "type",
      "attribute",
      "value"
    ]
  },
  {
    "group_id": 4413608323917257022,
    "candidate_ids": [
      1469747340395296995,
      17697405109260207715
    ],
    "field_score_matrix": [
      [
        0.8,
        0.9,
        0.9,
        0.9
      ],
      [
        0.9,
        0.9,
        0.9,
        0.9
      ]
    ],
    "field_order": [
      "entity",
      "type",
      "attribute",
      "value"
    ]
  },
  {
    "group_id": 6230352497543436655,
    "candidate_ids": [
      14570884922464568404,
      16785859557272971248
    ],
    "field_score_matrix": [
      [
        0.8,
        0.9,
        0.9,
        0.9
      ],
      [
        0.9,
        0.9,
        0.9,
        0.9
      ]
    ],
    "field_order": [
      "entity",
      "type",
      "attribute",
      "value"
    ]
  }
]