[
  {
    "candidate_id": 16849124883208172465,
    "entity": "Office of Emergency Services",
    "type": "government agency",
    "attribute": "restriction",
    "value": "extended to June 30, 2027",
    "entity_evidence": [
      {
        "span_id": 10037306156973799876,
        "start": 150276,
        "end": 150297,
        "text": "Office of Emergency Services",
        "chunk_id": 11281647413385897471
      }
    ],
    "type_evidence": [
      {
        "span_id": 17704358518936960624,
        "start": 150276,
        "end": 150297,
        "text": "Office of Emergency Services",
        "chunk_id": 11281647413385897471
      }
    ],
    "attribute_evidence": [
      {
        "span_id": 10798795412908535673,
        "start": 150276,
        "end": 150297,
        "text": "Office of Emergency Services",
        "chunk_id": 11281647413385897471
      }
    ],
    "value_evidence": [
      {
        "span_id": 354105337869273601,
        "start": 150276,
        "end": 150297,
        "text": "Office of Emergency Services",
        "chunk_id": 11281647413385897471
      }
    ]
  },
  {
    "candidate_id": 1505707545290708482,
    "entity": "California Specialized Training Institute",
    "type": "infrastructure",
    "attribute": "restriction",
    "value": "deferred maintenance",
    "entity_evidence": [
      {
        "span_id": 8565036886490452663,
        "start": 150246,
        "end": 150275,
        "text": "California Specialized Training Institute",
        "chunk_id": 11281647413385897471
      }
    ],
    "type_evidence": [
      {
        "span_id": 17224501307809148432,
        "start": 150246,
        "end": 150275,
        "text": "California Specialized Training Institute",
        "chunk_id": 11281647413385897471
      }
    ],
    "attribute_evidence": [
      {
        "span_id": 836309962320999163,
        "start": 150246,
        "end": 150275,
        "text": "California Specialized Training Institute",
        "chunk_id": 11281647413385897471
      }
    ],
    "value_evidence": [
      {
        "span_id": 6306306684969718495,
        "start": 150246,
        "end": 150275,
        "text": "California Specialized Training Institute",
        "chunk_id": 11281647413385897471
      }
    ]
  }
]