{
  "raw_response": "{\n  \"candidates\": [\n    {\n      \"entity\": \"San Francisco Bay Conservation and Development Commission\",\n      \"type\": \"government agency\",\n      \"attribute\": \"restriction\",\n      \"value\": \"not subject to provisions of subdivision (b) of Section 15.14\",\n      \"entity_evidence\": [\n        {\"start\": 123, \"end\": 143, \"text\": \"San Francisco Bay Conservation and Development Commission\"}\n      ],\n      \"type_evidence\": [\n        {\"start\": 123, \"end\": 143, \"text\": \"government agency\"}\n      ],\n      \"attribute_evidence\": [\n        {\"start\": 123, \"end\": 143, \"text\": \"restriction\"}\n      ],\n      \"value_evidence\": [\n        {\"start\": 123, \"end\": 143, \"text\": \"not subject to provisions of subdivision (b) of Section 15.14\"}\n      ]\n    },\n    {\n      \"entity\": \"San Gabriel and Lower Los Angeles Rivers and Mountains Conservancy\",\n      \"type\": \"government agency\",\n      \"attribute\": \"promotion\",\n      \"value\": \"629,000\",\n      \"entity_evidence\": [\n        {\"start\": 245, \"end\": 265, \"text\": \"San Gabriel and Lower Los Angeles Rivers and Mountains Conservancy\"}\n      ],\n      \"type_evidence\": [\n        {\"start\": 245, \"end\": 265, \"text\": \"government agency\"}\n      ],\n      \"attribute_evidence\": [\n        {\"start\": 245, \"end\": 265, \"text\": \"promotion\"}\n      ],\n      \"value_evidence\": [\n        {\"start\": 245, \"end\": 255, \"text\": \"629,000\"}\n      ]\n    }\n  ]\n}"
}