[
  {
    "candidate_id": 10765349620010248575,
    "entity": "California High School Proficiency Examination",
    "type": "technology",
    "attribute": "promotion",
    "value": "reimbursements",
    "entity_evidence": [
      {
        "span_id": 3535377453726395700,
        "start": 1045822,
        "end": 1045833,
        "text": "reimbursements",
        "chunk_id": 14748895672288218756
      }
    ],
    "type_evidence": [
      {
        "span_id": 14319733543563476445,
        "start": 1045822,
        "end": 1045833,
        "text": "reimbursements",
        "chunk_id": 14748895672288218756
      }
    ],
    "attribute_evidence": [
      {
        "span_id": 2210402179800672157,
        "start": 1045822,
        "end": 1045833,
        "text": "reimbursements",
        "chunk_id": 14748895672288218756
      }
    ],
    "value_evidence": [
      {
        "span_id": 7006006450373773308,
        "start": 1045822,
        "end": 1045833,
        "text": "reimbursements",
        "chunk_id": 14748895672288218756
      }
    ]
  },
  {
    "candidate_id": 14707858653034013224,
    "entity": "School Fiscal Services Division",
    "type": "infrastructure",
    "attribute": "restriction",
    "value": "deferrals and average daily attendance changes",
    "entity_evidence": [
      {
        "span_id": 8841382435940599769,
        "start": 1046104,
        "end": 1046117,
        "text": "School Fiscal Services Division",
        "chunk_id": 14748895672288218756
      }
    ],
    "type_evidence": [
      {
        "span_id": 2611208114917824292,
        "start": 1046104,
        "end": 1046117,
        "text": "School Fiscal Services Division",
        "chunk_id": 14748895672288218756
      }
    ],
    "attribute_evidence": [
      {
        "span_id": 15866819310968665628,
        "start": 1046104,
        "end": 1046117,
        "text": "School Fiscal Services Division",
        "chunk_id": 14748895672288218756
      }
    ],
    "value_evidence": [
      {
        "span_id": 8079636508267039727,
        "start": 1046104,
        "end": 1046117,
        "text": "School Fiscal Services Division",
        "chunk_id": 14748895672288218756
      }
    ]
  }
]