{
  "raw_response": "{\n  \"candidates\": [\n    {\n      \"entity\": \"Individuals with Disabilities Education Act\",\n      \"type\": \"government agency\",\n      \"attribute\": \"restriction\",\n      \"value\": \"federal\",\n      \"entity_evidence\": [\n        {\"start\": 0, \"end\": 29, \"text\": \"ederal Individuals with Disabilities Education Act\"}\n      ],\n      \"type_evidence\": [\n        {\"start\": 29, \"end\": 45, \"text\": \"Individuals with Disabilities Education Act\"}\n      ],\n      \"attribute_evidence\": [\n        {\"start\": 45, \"end\": 54, \"text\": \"funds shall be made available\"}\n      ],\n      \"value_evidence\": [\n        {\"start\": 54, \"end\": 59, \"text\": \"federal\"}\n      ]\n    },\n    {\n      \"entity\": \"Family Empowerment Center on Disability\",\n      \"type\": \"infrastructure\",\n      \"attribute\": \"restriction\",\n      \"value\": \"continued funding eligibility assessment\",\n      \"entity_evidence\": [\n        {\"start\": 59, \"end\": 76, \"text\": \"Family Empowerment Center on Disability\"}\n      ],\n      \"type_evidence\": [\n        {\"start\": 76, \"end\": 92, \"text\": \"Family Empowerment Center on Disability\"}\n      ],\n      \"attribute_evidence\": [\n        {\"start\": 92, \"end\": 105, \"text\": \"has been identified by the Superintendent as being subject to a continued funding eligibility assessment\"}\n      ],\n      \"value_evidence\": [\n        {\"start\": 105, \"end\": 128, \"text\": \"continued funding eligibility assessment\"}\n      ]\n    }\n  ]\n}"
}