{
  "raw_response": "{\n  \"candidates\": [\n    {\n      \"entity\": \"California Community Colleges\",\n      \"type\": \"government agency\",\n      \"attribute\": \"restriction\",\n      \"value\": \"mandates pursuant to Chapter 737 of the Statutes of 2004\",\n      \"entity_evidence\": [\n        {\"start\": 123, \"end\": 143, \"text\": \"mandates pursuant to Chapter 737 of the Statutes of 2004\"}\n      ]\n    ,\n    \"type_evidence\": [\n      {\"start\": 123, \"end\": 143, \"text\": \"mandates pursuant to Chapter 737 of the Statutes of 2004\"}\n    ]\n  ,\n    \"attribute_evidence\": [\n      {\"start\": 123, \"end\": 143, \"text\": \"mandates pursuant to Chapter 737 of the Statutes of 2004\"}\n    ]\n  ,\n    \"value_evidence\": [\n      {\"start\": 123, \"end\": 143, \"text\": \"mandates pursuant to Chapter 737 of the Statutes of 2004\"}\n    ]\n  },\n    {\n      \"entity\": \"California Community Colleges\",\n      \"type\": \"government agency\",\n      \"attribute\": \"subsidy\",\n      \"value\": \"additional textbook assistance grants\",\n      \"entity_evidence\": [\n        {\"start\": 0, \"end\": 24, \"text\": \"California Community Colleges\"}\n      ]\n    ,\n    \"type_evidence\": [\n      {\"start\": 0, \"end\": 24, \"text\": \"California Community Colleges\"}\n    ]\n  ,\n    \"attribute_evidence\": [\n      {\"start\": 0, \"end\": 24, \"text\": \"California Community Colleges\"}\n    ]\n  ,\n    \"value_evidence\": [\n      {\"start\": 0, \"end\": 24, \"text\": \"California Community Colleges\"}\n    ]\n  }\n] \n}"
}