{
  "raw_response": "{\n  \"candidates\": [\n    {\n      \"entity\": \"Office of Environmental Health Hazard Assessment\",\n      \"type\": \"government agency\",\n      \"attribute\": \"restriction\",\n      \"value\": \"until June 30, 2026\",\n      \"entity_evidence\": [\n        {\"start\": 14, \"end\": 43, \"text\": \"Office of Environmental Health Hazard Assessment\"}\n      ]\n    ,\n    \"type_evidence\": [\n        {\"start\": 14, \"end\": 43, \"text\": \"Office of Environmental Health Hazard Assessment\"}\n      ]\n    ,\n    \"attribute_evidence\": [\n        {\"start\": 14, \"end\": 43, \"text\": \"Office of Environmental Health Hazard Assessment\"}\n      ]\n    ,\n    \"value_evidence\": [\n        {\"start\": 14, \"end\": 43, \"text\": \"Office of Environmental Health Hazard Assessment\"}\n      ]\n    },\n    {\n      \"entity\": \"State Council on Developmental Disabilities\",\n      \"type\": \"government agency\",\n      \"attribute\": \"reappropriation\",\n      \"value\": \"until June 30, 2026\",\n      \"entity_evidence\": [\n        {\"start\": 114, \"end\": 143, \"text\": \"State Council on Developmental Disabilities\"}\n      ]\n    ,\n    \"type_evidence\": [\n        {\"start\": 114, \"end\": 143, \"text\": \"State Council on Developmental Disabilities\"}\n      ]\n    ,\n    \"attribute_evidence\": [\n        {\"start\": 114, \"end\": 143, \"text\": \"State Council on Developmental Disabilities\"}\n      ]\n    ,\n    \"value_evidence\": [\n        {\"start\": 114, \"end\": 143, \"text\": \"State Council on Developmental Disabilities\"}\n      ]\n    }\n  ]\n}"
}