[
  {
    "candidate_id": 15049965007772925277,
    "entity": "State Department of State Hospitals",
    "type": "government agency",
    "attribute": "regulation",
    "value": "exemption",
    "entity_evidence": [
      {
        "span_id": 8971812318220839765,
        "start": 882654,
        "end": 882676,
        "text": "State Department of State Hospitals",
        "chunk_id": 8922208804064631192
      }
    ],
    "type_evidence": [
      {
        "span_id": 15962875508746977019,
        "start": 882654,
        "end": 882676,
        "text": "government agency",
        "chunk_id": 8922208804064631192
      }
    ],
    "attribute_evidence": [
      {
        "span_id": 8903002480912650511,
        "start": 882654,
        "end": 882676,
        "text": "regulation",
        "chunk_id": 8922208804064631192
      }
    ],
    "value_evidence": [
      {
        "span_id": 16446459812434713086,
        "start": 882654,
        "end": 882676,
        "text": "exemption",
        "chunk_id": 8922208804064631192
      }
    ]
  },
  {
    "candidate_id": 8832955767423348729,
    "entity": "Electronic Health Record Continuum Project",
    "type": "technology",
    "attribute": "regulation",
    "value": "exemption",
    "entity_evidence": [
      {
        "span_id": 17672987554442705952,
        "start": 883444,
        "end": 883466,
        "text": "Electronic Health Record Continuum Project",
        "chunk_id": 8922208804064631192
      }
    ],
    "type_evidence": [
      {
        "span_id": 7854494762695639867,
        "start": 883444,
        "end": 883466,
        "text": "technology",
        "chunk_id": 8922208804064631192
      }
    ],
    "attribute_evidence": [
      {
        "span_id": 7420209305508944336,
        "start": 883444,
        "end": 883466,
        "text": "regulation",
        "chunk_id": 8922208804064631192
      }
    ],
    "value_evidence": [
      {
        "span_id": 11470479551337817181,
        "start": 883444,
        "end": 883466,
        "text": "exemption",
        "chunk_id": 8922208804064631192
      }
    ]
  }
]