[
  {
    "refined_id": 6515649900420940172,
    "source_group_id": 10320374106740076743,
    "source_candidate_ids": [
      16085837682313418161
    ],
    "entity": "State Water Resources Control Board",
    "type": "government agency",
    "attribute": "support",
    "value": "fully",
    "entity_evidence": [
      {
        "span_id": 4836586560759082731,
        "start": 722692,
        "end": 722717,
        "text": "State Water Resources Control Board",
        "chunk_id": 11942630893851428071
      }
    ],
    "type_evidence": [
      {
        "span_id": 15127906845475942141,
        "start": 722692,
        "end": 722717,
        "text": "State Water Resources Control Board",
        "chunk_id": 11942630893851428071
      }
    ],
    "attribute_evidence": [
      {
        "span_id": 14533947125668201537,
        "start": 722692,
        "end": 722717,
        "text": "State Water Resources Control Board",
        "chunk_id": 11942630893851428071
      }
    ],
    "value_evidence": [
      {
        "span_id": 4356239162401310349,
        "start": 722692,
        "end": 722717,
        "text": "State Water Resources Control Board",
        "chunk_id": 11942630893851428071
      }
    ]
  }
]