[
  {
    "refined_id": 7106000769728018979,
    "source_group_id": 13830248872609978857,
    "source_candidate_ids": [
      14994640487959589308
    ],
    "entity": "California State University",
    "type": "government agency",
    "attribute": "restriction",
    "value": "supplemental funding",
    "entity_evidence": [
      {
        "span_id": 16363554314262334751,
        "start": 1362379,
        "end": 1362399,
        "text": "The California State University",
        "chunk_id": 6589264734715255249
      }
    ],
    "type_evidence": [
      {
        "span_id": 14749611031369646621,
        "start": 1362379,
        "end": 1362399,
        "text": "The California State University",
        "chunk_id": 6589264734715255249
      }
    ],
    "attribute_evidence": [
      {
        "span_id": 10661953070440064917,
        "start": 1362401,
        "end": 1362411,
        "text": "to provide summer-term financial aid",
        "chunk_id": 6589264734715255249
      }
    ],
    "value_evidence": [
      {
        "span_id": 11775459369273348048,
        "start": 1362401,
        "end": 1362411,
        "text": "to provide summer-term financial aid",
        "chunk_id": 6589264734715255249
      }
    ]
  }
]