[
  {
    "refined_id": 8238781858719518259,
    "source_group_id": 14647897061572667079,
    "source_candidate_ids": [
      8395378625158823565
    ],
    "entity": "Commission on Peace Officer Standards and Training",
    "type": "government agency",
    "attribute": "restriction",
    "value": "specific",
    "entity_evidence": [
      {
        "span_id": 10067886169462248618,
        "start": 1600825,
        "end": 1600845,
        "text": "Commission on Peace Officer Standards and Training",
        "chunk_id": 10345120031829729478
      }
    ],
    "type_evidence": [
      {
        "span_id": 8658452138893277532,
        "start": 1600825,
        "end": 1600845,
        "text": "government agency",
        "chunk_id": 10345120031829729478
      }
    ],
    "attribute_evidence": [
      {
        "span_id": 16284938438526665284,
        "start": 1600825,
        "end": 1600845,
        "text": "restriction",
        "chunk_id": 10345120031829729478
      }
    ],
    "value_evidence": [
      {
        "span_id": 1085532506738316686,
        "start": 1600825,
        "end": 1600845,
        "text": "specific",
        "chunk_id": 10345120031829729478
      }
    ]
  }
]