[
  {
    "refined_id": 12218656969938756988,
    "source_group_id": 14681395491879801825,
    "source_candidate_ids": [
      10841679789999212788,
      312276760233952124
    ],
    "entity": "State Water Resources Control Board",
    "type": "government agency",
    "attribute": "restriction",
    "value": "until June 30, 2028",
    "entity_evidence": [
      {
        "span_id": 135118155028403467,
        "start": 727638,
        "end": 727658,
        "text": "State Water Resources Control Board",
        "chunk_id": 12924325562064581144
      }
    ],
    "type_evidence": [
      {
        "span_id": 17661956677734923633,
        "start": 727638,
        "end": 727658,
        "text": "government agency",
        "chunk_id": 12924325562064581144
      }
    ],
    "attribute_evidence": [
      {
        "span_id": 7799664302956304681,
        "start": 727638,
        "end": 727658,
        "text": "restriction",
        "chunk_id": 12924325562064581144
      }
    ],
    "value_evidence": [
      {
        "span_id": 13092025946872380582,
        "start": 727638,
        "end": 727658,
        "text": "until June 30, 2028",
        "chunk_id": 12924325562064581144
      }
    ]
  }
]