{
  "raw_response": "{\n  \"refined_quadruplets\": [\n    {\n      \"source_candidate_ids\": [\n        14606005402342909087\n      ],\n      \"entity\": \"local educational agency (LEA)\",\n      \"type\": \"government agency\",\n      \"attribute\": \"restriction\",\n      \"value\": \"fiscal accountability policies and procedures\",\n      \"entity_evidence\": [\n        {\n          \"start\": 1837731,\n          \"end\": 1837751,\n          \"text\": \"local educational agency (LEA)\",\n          \"chunk_id\": 3665063470177479453\n        }\n      ],\n      \"type_evidence\": [\n        {\n          \"start\": 1837731,\n          \"end\": 1837751,\n          \"text\": \"local educational agency (LEA)\",\n          \"chunk_id\": 3665063470177479453\n        }\n      ],\n      \"attribute_evidence\": [\n        {\n          \"start\": 1837731,\n          \"end\": 1837751,\n          \"text\": \"shall be subject to the LEA's fiscal accountability policies and procedures.\",\n          \"chunk_id\": 3665063470177479453\n        }\n      ],\n      \"value_evidence\": [\n        {\n          \"start\": 1837731,\n          \"end\": 1837751,\n          \"text\": \"fiscal accountability policies and procedures\",\n          \"chunk_id\": 3665063470177479453\n        }\n      ]\n    }\n  ],\n  \"refinement_artifact\": {\n    \"candidate_ids\": [\n      14606005402342909087\n    ],\n    \"entity_relations\": [\n      [\n        \"support\",\n        \"support\",\n        \"support\",\n        \"support\"\n      ]\n    ],\n    \"type_relations\": [\n      [\n        \"support\",\n        \"support\",\n        \"support\",\n        \"support\"\n      ]\n    ],\n    \"attribute_relations\": [\n      [\n        \"support\",\n        \"support\",\n        \"support\",\n        \"support\"\n      ]\n    ],\n    \"value_relations\": [\n      [\n        \"support\",\n        \"support\",\n        \"support\",\n        \"support\"\n      ]\n    ]\n  }\n}"
}