[
  {
    "refined_id": 4720141060810474616,
    "source_group_id": 16273950010709325300,
    "source_candidate_ids": [
      2011104874052476508
    ],
    "entity": "Director of Finance",
    "type": "government agency",
    "attribute": "restriction",
    "value": "partial",
    "entity_evidence": [
      {
        "span_id": 2518575942878713098,
        "start": 952323,
        "end": 952343,
        "text": "Director of Finance",
        "chunk_id": 14468173538684347185
      }
    ],
    "type_evidence": [
      {
        "span_id": 5795420272570587577,
        "start": 952323,
        "end": 952343,
        "text": "government agency",
        "chunk_id": 14468173538684347185
      }
    ],
    "attribute_evidence": [
      {
        "span_id": 14314680550776055623,
        "start": 952323,
        "end": 952343,
        "text": "restriction",
        "chunk_id": 14468173538684347185
      }
    ],
    "value_evidence": [
      {
        "span_id": 6227987412428601977,
        "start": 952323,
        "end": 952343,
        "text": "partial",
        "chunk_id": 14468173538684347185
      }
    ]
  }
]