{
  "raw_response": "{\n  \"refined_quadruplets\": [\n    {\n      \"source_candidate_ids\": [\n        11590120297375456474\n      ],\n      \"entity\": \"Director of Finance\",\n      \"type\": \"government agency\",\n      \"attribute\": \"restriction\",\n      \"value\": \"temporary or permanent redirection of funds\",\n      \"entity_evidence\": [\n        {\n          \"start\": 501271,\n          \"end\": 501294,\n          \"text\": \"Notwithstanding any other law, the Director of Finance may authorize the temporary or permanent redirection of funds\",\n          \"chunk_id\": 10016127979066947407\n        }\n      ],\n      \"type_evidence\": [\n        {\n          \"start\": 501271,\n          \"end\": 501294,\n          \"text\": \"Notwithstanding any other law, the Director of Finance may authorize the temporary or permanent redirection of funds\",\n          \"chunk_id\": 10016127979066947407\n        }\n      ],\n      \"attribute_evidence\": [\n        {\n          \"start\": 501271,\n          \"end\": 501294,\n          \"text\": \"Notwithstanding any other law, the Director of Finance may authorize the temporary or permanent redirection of funds\",\n          \"chunk_id\": 10016127979066947407\n        }\n      ],\n      \"value_evidence\": [\n        {\n          \"start\": 501271,\n          \"end\": 501294,\n          \"text\": \"Notwithstanding any other law, the Director of Finance may authorize the temporary or permanent redirection of funds\",\n          \"chunk_id\": 10016127979066947407\n        }\n      ]\n    }\n  ],\n  \"refinement_artifact\": {\n    \"candidate_ids\": [\n      11590120297375456474\n    ],\n    \"entity_relations\": [\n      [\n        \"support\",\n        \"support\",\n        \"support\",\n        \"support\"\n      ]\n    ],\n    \"type_relations\": [\n      [\n        \"support\",\n        \"support\",\n        \"support\",\n        \"support\"\n      ]\n    ],\n    \"attribute_relations\": [\n      [\n        \"support\",\n        \"support\",\n        \"support\",\n        \"support\"\n      ]\n    ],\n    \"value_relations\": [\n      [\n        \"support\",\n        \"support\",\n        \"support\",\n        \"support\"\n      ]\n    ]\n  }\n}"
}