{
  "raw_response": "{\n  \"refined_quadruplets\": [\n    {\n      \"source_candidate_ids\": [\n        1095379685881121642\n      ],\n      \"entity\": \"Department of Human Resources\",\n      \"type\": \"government agency\",\n      \"attribute\": \"restriction\",\n      \"value\": \"aggregate amount of General Fund appropriation decreases\",\n      \"entity_evidence\": [\n        {\n          \"start\": 1521671,\n          \"end\": 1521691,\n          \"text\": \"Department of Human Resources\",\n          \"chunk_id\": 13205798270827756164\n        }\n      ],\n      \"type_evidence\": [\n        {\n          \"start\": 1521671,\n          \"end\": 1521691,\n          \"text\": \"government agency\",\n          \"chunk_id\": 13205798270827756164\n        }\n      ],\n      \"attribute_evidence\": [\n        {\n          \"start\": 1521671,\n          \"end\": 1521691,\n          \"text\": \"restriction\",\n          \"chunk_id\": 13205798270827756164\n        }\n      ],\n      \"value_evidence\": [\n        {\n          \"start\": 1521671,\n          \"end\": 1521691,\n          \"text\": \"aggregate amount of General Fund appropriation decreases\",\n          \"chunk_id\": 13205798270827756164\n        }\n      ]\n    }\n  ],\n  \"refinement_artifact\": {\n    \"candidate_ids\": [\n      1095379685881121642\n    ],\n    \"entity_relations\": [\n      [\n        \"support\",\n        \"support\",\n        \"support\",\n        \"support\"\n      ]\n    ],\n    \"type_relations\": [\n      [\n        \"support\",\n        \"support\",\n        \"support\",\n        \"support\"\n      ]\n    ],\n    \"attribute_relations\": [\n      [\n        \"support\",\n        \"support\",\n        \"support\",\n        \"support\"\n      ]\n    ],\n    \"value_relations\": [\n      [\n        \"support\",\n        \"support\",\n        \"support\",\n        \"support\"\n      ]\n    ]\n  }\n}"
}