{
  "raw_response": "{\n  \"refined_quadruplets\": [\n    {\n      \"source_candidate_ids\": [\n        17983393923848604619\n      ],\n      \"entity\": \"California Debt Limit Allocation Committee\",\n      \"type\": \"government agency\",\n      \"attribute\": \"restriction\",\n      \"value\": \"excess of the amount appropriated\",\n      \"entity_evidence\": [\n        {\n          \"start\": 235833,\n          \"end\": 235861,\n          \"text\": \"California Debt Limit Allocation Committee\",\n          \"chunk_id\": 12277709146583531180\n        }\n      ],\n      \"type_evidence\": [\n        {\n          \"start\": 235833,\n          \"end\": 235861,\n          \"text\": \"California Debt and Investment Advisory Commission\",\n          \"chunk_id\": 12277709146583531180\n        }\n      ],\n      \"attribute_evidence\": [\n        {\n          \"start\": 235861,\n          \"end\": 235879,\n          \"text\": \"expenditures for the California Debt and Investment Advisory Commission\",\n          \"chunk_id\": 12277709146583531180\n        }\n      ],\n      \"value_evidence\": [\n        {\n          \"start\": 235861,\n          \"end\": 235879,\n          \"text\": \"expenditures for the California Debt and Investment Advisory Commission\",\n          \"chunk_id\": 12277709146583531180\n        }\n      ]\n    }\n  ],\n  \"refinement_artifact\": {\n    \"candidate_ids\": [\n      17983393923848604619\n    ],\n    \"entity_relations\": [\n      [\n        \"support\",\n        \"support\",\n        \"support\",\n        \"support\"\n      ]\n    ],\n    \"type_relations\": [\n      [\n        \"support\",\n        \"support\",\n        \"support\",\n        \"support\"\n      ]\n    ],\n    \"attribute_relations\": [\n      [\n        \"support\",\n        \"support\",\n        \"support\",\n        \"support\"\n      ]\n    ],\n    \"value_relations\": [\n      [\n        \"support\",\n        \"support\",\n        \"support\",\n        \"support\"\n      ]\n    ]\n  }\n}"
}