[
  {
    "refined_id": 2356202616335048467,
    "source_group_id": 5395826602996555959,
    "source_candidate_ids": [
      9541572258564935927
    ],
    "entity": "Commission on Peace Officer Standards and Training",
    "type": "government agency",
    "attribute": "restriction",
    "value": "limited",
    "entity_evidence": [
      {
        "span_id": 16335355959556884343,
        "start": 1603223,
        "end": 1603243,
        "text": "Commission on Peace Officer Standards and Training",
        "chunk_id": 1619159163588987989
      }
    ],
    "type_evidence": [
      {
        "span_id": 15448294252727787332,
        "start": 1603223,
        "end": 1603243,
        "text": "government agency",
        "chunk_id": 1619159163588987989
      }
    ],
    "attribute_evidence": [
      {
        "span_id": 12548198627339151125,
        "start": 1603223,
        "end": 1603243,
        "text": "restriction",
        "chunk_id": 1619159163588987989
      }
    ],
    "value_evidence": [
      {
        "span_id": 14544835207339789720,
        "start": 1603223,
        "end": 1603243,
        "text": "limited",
        "chunk_id": 1619159163588987989
      }
    ]
  }
]