[
  {
    "refined_id": 13729799876226005202,
    "source_group_id": 5607217241779402506,
    "source_candidate_ids": [
      7253973144412520082
    ],
    "entity": "Transit and Intercity Rail Capital Program",
    "type": "infrastructure",
    "attribute": "restriction",
    "value": "specific uses",
    "entity_evidence": [
      {
        "span_id": 5277150060979329710,
        "start": 89459,
        "end": 89480,
        "text": "Transit and Intercity Rail Capital Program",
        "chunk_id": 15369430325802398534
      }
    ],
    "type_evidence": [
      {
        "span_id": 5953144965009201665,
        "start": 89459,
        "end": 89480,
        "text": "Transit and Intercity Rail Capital Program",
        "chunk_id": 15369430325802398534
      }
    ],
    "attribute_evidence": [
      {
        "span_id": 3625873895138458313,
        "start": 89459,
        "end": 89480,
        "text": "Transit and Intercity Rail Capital Program",
        "chunk_id": 15369430325802398534
      }
    ],
    "value_evidence": [
      {
        "span_id": 714139827457822856,
        "start": 89459,
        "end": 89480,
        "text": "Transit and Intercity Rail Capital Program",
        "chunk_id": 15369430325802398534
      }
    ]
  }
]