[
  {
    "refined_id": 8220949259779276648,
    "source_group_id": 7758338997640469720,
    "source_candidate_ids": [
      17707638066248538739
    ],
    "entity": "Office of Diversity, Equity, and Inclusion",
    "type": "government agency",
    "attribute": "restriction",
    "value": "consistent with the emergency management system",
    "entity_evidence": [
      {
        "span_id": 6130201787694110621,
        "start": 149774,
        "end": 149801,
        "text": "Office of Diversity, Equity, and Inclusion",
        "chunk_id": 7210730480251496744
      }
    ],
    "type_evidence": [
      {
        "span_id": 4932033208177827550,
        "start": 149774,
        "end": 149801,
        "text": "Office of Diversity, Equity, and Inclusion",
        "chunk_id": 7210730480251496744
      }
    ],
    "attribute_evidence": [
      {
        "span_id": 11919100465967746549,
        "start": 149774,
        "end": 149801,
        "text": "Office of Diversity, Equity, and Inclusion",
        "chunk_id": 7210730480251496744
      }
    ],
    "value_evidence": [
      {
        "span_id": 15719476259116200479,
        "start": 149774,
        "end": 149801,
        "text": "Office of Diversity, Equity, and Inclusion",
        "chunk_id": 7210730480251496744
      }
    ]
  }
]