{
  "raw_response": "{\n  \"refined_quadruplets\": [\n    {\n      \"source_candidate_ids\": [\n        18291047161318604057,\n        16832673101396819410\n      ],\n      \"entity\": \"frontier developer\",\n      \"type\": \"government agency\",\n      \"attribute\": \"restriction\",\n      \"value\": \"prohibition\",\n      \"entity_evidence\": [\n        {\n          \"start\": 30184,\n          \"end\": 30197,\n          \"text\": \"A frontier developer\",\n          \"chunk_id\": 7795682431347896540\n        }\n      ],\n      \"type_evidence\": [\n        {\n          \"start\": 30184,\n          \"end\": 30197,\n          \"text\": \"A frontier developer\",\n          \"chunk_id\": 7795682431347896540\n        }\n      ],\n      \"attribute_evidence\": [\n        {\n          \"start\": 30197,\n          \"end\": 30202,\n          \"text\": \"shall not\",\n          \"chunk_id\": 7795682431347896540\n        }\n      ],\n      \"value_evidence\": [\n        {\n          \"start\": 30202,\n          \"end\": 30207,\n          \"text\": \"prevent\",\n          \"chunk_id\": 7795682431347896540\n        }\n      ]\n    }\n  ],\n  \"refinement_artifact\": {\n    \"candidate_ids\": [\n      18291047161318604057,\n      16832673101396819410\n    ],\n    \"entity_relations\": [\n      [\n        \"support\",\n        \"support\"\n      ],\n      [\n        \"support\",\n        \"support\"\n      ]\n    ],\n    \"type_relations\": [\n      [\n        \"support\",\n        \"support\"\n      ],\n      [\n        \"support\",\n        \"support\"\n      ]\n    ],\n    \"attribute_relations\": [\n      [\n        \"support\",\n        \"support\"\n      ],\n      [\n        \"support\",\n        \"support\"\n      ]\n    ],\n    \"value_relations\": [\n      [\n        \"support\",\n        \"support\"\n      ],\n      [\n        \"support\",\n        \"support\"\n      ]\n    ]\n  }\n}"
}