{
  "raw_response": "{\n  \"candidates\": [\n    {\n      \"entity\": \"frontier developer\",\n      \"type\": \"government agency\",\n      \"attribute\": \"restriction\",\n      \"value\": \"prohibition\",\n      \"entity_evidence\": [\n        {\"start\": 110, \"end\": 123, \"text\": \"A frontier developer\"}\n      ],\n      \"type_evidence\": [\n        {\"start\": 110, \"end\": 123, \"text\": \"A frontier developer\"}\n      ],\n      \"attribute_evidence\": [\n        {\"start\": 123, \"end\": 128, \"text\": \"shall not\"}\n      ],\n      \"value_evidence\": [\n        {\"start\": 128, \"end\": 133, \"text\": \"prevent\"}\n      ]\n    },\n    {\n      \"entity\": \"covered employee\",\n      \"type\": \"individual\",\n      \"attribute\": \"restriction\",\n      \"value\": \"prohibition\",\n      \"entity_evidence\": [\n        {\"start\": 234, \"end\": 247, \"text\": \"A covered employee\"}\n      ],\n      \"type_evidence\": [\n        {\"start\": 234, \"end\": 247, \"text\": \"A covered employee\"}\n      ],\n      \"attribute_evidence\": [\n        {\"start\": 247, \"end\": 252, \"text\": \"may use\"}\n      ],\n      \"value_evidence\": [\n        {\"start\": 252, \"end\": 257, \"text\": \"make reports\"}\n      ]\n    }\n  ]\n}"
}