[
  {
    "refined_id": 6276163410757801328,
    "source_group_id": 4842386379895557223,
    "source_candidate_ids": [
      6087689068188797244
    ],
    "entity": "State Department of Education",
    "type": "government agency",
    "attribute": "restriction",
    "value": "limited",
    "entity_evidence": [
      {
        "span_id": 5160230234285942272,
        "start": 74714,
        "end": 74730,
        "text": "The State Department of Education",
        "chunk_id": 11064768810285638684
      }
    ],
    "type_evidence": [
      {
        "span_id": 3191826969996058571,
        "start": 74714,
        "end": 74730,
        "text": "The State Department of Education",
        "chunk_id": 11064768810285638684
      }
    ],
    "attribute_evidence": [
      {
        "span_id": 2528145760260654667,
        "start": 74714,
        "end": 74730,
        "text": "The State Department of Education",
        "chunk_id": 11064768810285638684
      }
    ],
    "value_evidence": [
      {
        "span_id": 18280485374397550291,
        "start": 74714,
        "end": 74730,
        "text": "The State Department of Education",
        "chunk_id": 11064768810285638684
      }
    ]
  }
]