{
  "raw_response": "{\n  \"refined_quadruplets\": [\n    {\n      \"source_candidate_ids\": [\n        7920649973299646049,\n        10038128694493686884\n      ],\n      \"entity\": \"State Department of Education\",\n      \"type\": \"government agency\",\n      \"attribute\": \"regulation\",\n      \"value\": \"oversight\",\n      \"entity_evidence\": [\n        {\n          \"start\": 47934,\n          \"end\": 47955,\n          \"text\": \"State Department of Education\",\n          \"chunk_id\": 17761956045604809607\n        }\n      ],\n      \"type_evidence\": [\n        {\n          \"start\": 47934,\n          \"end\": 47955,\n          \"text\": \"government agency\",\n          \"chunk_id\": 17761956045604809607\n        }\n      ],\n      \"attribute_evidence\": [\n        {\n          \"start\": 47934,\n          \"end\": 47955,\n          \"text\": \"regulation\",\n          \"chunk_id\": 17761956045604809607\n        }\n      ],\n      \"value_evidence\": [\n        {\n          \"start\": 47934,\n          \"end\": 47955,\n          \"text\": \"oversight\",\n          \"chunk_id\": 17761956045604809607\n        }\n      ]\n    }\n  ],\n  \"refinement_artifact\": {\n    \"candidate_ids\": [\n      7920649973299646049,\n      10038128694493686884\n    ],\n    \"entity_relations\": [\n      [\n        \"support\",\n        \"support\"\n      ],\n      [\n        \"support\",\n        \"support\"\n      ]\n    ],\n    \"type_relations\": [\n      [\n        \"support\",\n        \"support\"\n      ],\n      [\n        \"support\",\n        \"support\"\n      ]\n    ],\n    \"attribute_relations\": [\n      [\n        \"support\",\n        \"support\"\n      ],\n      [\n        \"support\",\n        \"support\"\n      ]\n    ],\n    \"value_relations\": [\n      [\n        \"support\",\n        \"support\"\n      ],\n      [\n        \"support\",\n        \"support\"\n      ]\n    ]\n  }\n}"
}