[
  {
    "candidate_id": 9059785909989836710,
    "entity": "Alabama Math, Science and Technology Initiative Program (AMSTI)",
    "type": "technology",
    "attribute": "promotion",
    "value": "divided based upon the number of classroom teachers served",
    "entity_evidence": [
      {
        "span_id": 1710473240172090827,
        "start": 39853,
        "end": 39874,
        "text": "Alabama Math, Science and Technology Initiative Program (AMSTI)",
        "chunk_id": 16207215204831358817
      }
    ],
    "type_evidence": [
      {
        "span_id": 6684420919921787772,
        "start": 39853,
        "end": 39874,
        "text": "Alabama Math, Science and Technology Initiative Program (AMSTI)",
        "chunk_id": 16207215204831358817
      }
    ],
    "attribute_evidence": [
      {
        "span_id": 7549997367783377980,
        "start": 39853,
        "end": 39874,
        "text": "Alabama Math, Science and Technology Initiative Program (AMSTI)",
        "chunk_id": 16207215204831358817
      }
    ],
    "value_evidence": [
      {
        "span_id": 8305704842153633794,
        "start": 39853,
        "end": 39874,
        "text": "Alabama Math, Science and Technology Initiative Program (AMSTI)",
        "chunk_id": 16207215204831358817
      }
    ]
  },
  {
    "candidate_id": 14223506161779357,
    "entity": "State Department of Education",
    "type": "government agency",
    "attribute": "restriction",
    "value": "subject to appropriations",
    "entity_evidence": [
      {
        "span_id": 6562948106417503368,
        "start": 39734,
        "end": 39750,
        "text": "Education, State Department of:",
        "chunk_id": 16207215204831358817
      }
    ],
    "type_evidence": [
      {
        "span_id": 8433668642949306850,
        "start": 39734,
        "end": 39750,
        "text": "Education, State Department of:",
        "chunk_id": 16207215204831358817
      }
    ],
    "attribute_evidence": [
      {
        "span_id": 12167576313700430506,
        "start": 39734,
        "end": 39750,
        "text": "Education, State Department of:",
        "chunk_id": 16207215204831358817
      }
    ],
    "value_evidence": [
      {
        "span_id": 13234091501724789659,
        "start": 39734,
        "end": 39750,
        "text": "Education, State Department of:",
        "chunk_id": 16207215204831358817
      }
    ]
  }
]