{
  "raw_response": "{\n  \"candidates\": [\n    {\n      \"entity\": \"Alaska Aerospace Corporation\",\n      \"type\": \"company\",\n      \"attribute\": \"restriction\",\n      \"value\": \"limited\",\n      \"entity_evidence\": [\n        {\"start\": 134, \"end\": 155, \"text\": \"ALASKA AEROSPACE CORPORATION\"}\n      ]\n    ,\n    \"type_evidence\": [\n        {\"start\": 134, \"end\": 155, \"text\": \"ALASKA AEROSPACE CORPORATION\"}\n      ]\n    ,\n    \"attribute_evidence\": [\n        {\"start\": 134, \"end\": 155, \"text\": \"ALASKA AEROSPACE CORPORATION\"}\n      ]\n    ,\n    \"value_evidence\": [\n        {\"start\": 134, \"end\": 155, \"text\": \"ALASKA AEROSPACE CORPORATION\"}\n      ]\n    },\n    {\n      \"entity\": \"Alaska Housing Finance Corporation\",\n      \"type\": \"company\",\n      \"attribute\": \"restriction\",\n      \"value\": \"limited\",\n      \"entity_evidence\": [\n        {\"start\": 266, \"end\": 291, \"text\": \"ALASKA HOUSING FINANCE CORPORATION\"}\n      ]\n    ,\n    \"type_evidence\": [\n        {\"start\": 266, \"end\": 291, \"text\": \"ALASKA HOUSING FINANCE CORPORATION\"}\n      ]\n    ,\n    \"attribute_evidence\": [\n        {\"start\": 266, \"end\": 291, \"text\": \"ALASKA HOUSING FINANCE CORPORATION\"}\n      ]\n    ,\n    \"value_evidence\": [\n        {\"start\": 266, \"end\": 291, \"text\": \"ALASKA HOUSING FINANCE CORPORATION\"}\n      ]\n    }\n  ]\n}"
}