{
  "raw_response": "{\n  \"refined_quadruplets\": [\n    {\n      \"source_candidate_ids\": [\n        14570884922464568404,\n        16785859557272971248\n      ],\n      \"entity\": \"video streaming service\",\n      \"type\": \"technology\",\n      \"attribute\": \"restriction\",\n      \"value\": \"age-rating\",\n      \"entity_evidence\": [\n        {\n          \"start\": 33576,\n          \"end\": 33593,\n          \"text\": \"video streaming service\"\n        ,\n        \"chunk_id\": 16818202187050619486\n        }\n      ],\n      \"type_evidence\": [\n        {\n          \"start\": 33576,\n          \"end\": 33593,\n          \"text\": \"video streaming service\"\n        ,\n        \"chunk_id\": 16818202187050619486\n        }\n      ],\n      \"attribute_evidence\": [\n        {\n          \"start\": 33576,\n          \"end\": 33593,\n          \"text\": \"video streaming service\"\n        ,\n        \"chunk_id\": 16818202187050619486\n        }\n      ],\n      \"value_evidence\": [\n        {\n          \"start\": 33576,\n          \"end\": 33593,\n          \"text\": \"age-rating\"\n        ,\n        \"chunk_id\": 16818202187050619486\n        }\n      ]\n    }\n  ],\n  \"refinement_artifact\": null\n}"
}